MANIFEST.in
README.txt
setup.cfg
setup.py
autoneg/__init__.py
autoneg/accept.py
autoneg/app.py
autoneg/command.py
autoneg.egg-info/PKG-INFO
autoneg.egg-info/SOURCES.txt
autoneg.egg-info/dependency_links.txt
autoneg.egg-info/entry_points.txt
autoneg.egg-info/not-zip-safe
autoneg.egg-info/requires.txt
autoneg.egg-info/top_level.txt
docs/conf.py
docs/index.txt
examples/autoneg_config.py
examples/rdfan_config.py