Metadata-Version: 1.0
Name: autoneg
Version: 0.4
Summary: Simple Content Autonegotiation (F)CGI
Home-page: http://river.styx.org/~ww/2010/10/autoneg/
Author: William Waites
Author-email: ww@styx.org
License: BSD
Platform: UNKNOWN
